aiscraper/__init__.py
ai_scraper_toolkit-0.0.2.dist-info/LICENSE
ai_scraper_toolkit-0.0.2.dist-info/METADATA
ai_scraper_toolkit-0.0.2.dist-info/WHEEL
ai_scraper_toolkit-0.0.2.dist-info/top_level.txt
ai_scraper_toolkit-0.0.2.dist-info/RECORD
